ri/__init__.py
ri/client.py
ri/apiclient/__init__.py
ri/apiclient/api_client.py
ri/apiclient/api_response.py
ri/apiclient/configuration.py
ri/apiclient/exceptions.py
ri/apiclient/py.typed
ri/apiclient/rest.py
ri/apiclient/api/__init__.py
ri/apiclient/api/agent_manager_api.py
ri/apiclient/api/customer_managed_key_service_api.py
ri/apiclient/api/data_collector_api.py
ri/apiclient/api/detection_api.py
ri/apiclient/api/feature_flag_api.py
ri/apiclient/api/file_scanning_api.py
ri/apiclient/api/file_upload_api.py
ri/apiclient/api/firewall_service_api.py
ri/apiclient/api/generative_validation_api.py
ri/apiclient/api/image_registry_api.py
ri/apiclient/api/integration_service_api.py
ri/apiclient/api/job_reader_api.py
ri/apiclient/api/model_card_service_api.py
ri/apiclient/api/model_testing_api.py
ri/apiclient/api/monitor_service_api.py
ri/apiclient/api/notification_setting_api.py
ri/apiclient/api/project_service_api.py
ri/apiclient/api/registry_service_api.py
ri/apiclient/api/results_reader_api.py
ri/apiclient/api/rime_info_api.py
ri/apiclient/api/schedule_service_api.py
ri/apiclient/api/security_db_api.py
ri/apiclient/api/user_api.py
ri/apiclient/api/workspace_service_api.py
ri/apiclient/models/__init__.py
ri/apiclient/models/activate_schedule_for_project_request.py
ri/apiclient/models/activate_schedule_for_project_response.py
ri/apiclient/models/actor_role.py
ri/apiclient/models/add_users_to_project_request.py
ri/apiclient/models/add_users_to_workspace_request.py
ri/apiclient/models/agent.py
ri/apiclient/models/agent_desired_state.py
ri/apiclient/models/agent_status.py
ri/apiclient/models/agent_type.py
ri/apiclient/models/aggregated_metric.py
ri/apiclient/models/aggregation.py
ri/apiclient/models/aggregation_type.py
ri/apiclient/models/alert_level.py
ri/apiclient/models/annotated_test_config.py
ri/apiclient/models/any.py
ri/apiclient/models/api_token_info.py
ri/apiclient/models/archived_job_logs.py
ri/apiclient/models/artifact_identifier.py
robustintelligence-2.13.2.dist-info/METADATA
robustintelligence-2.13.2.dist-info/WHEEL
robustintelligence-2.13.2.dist-info/top_level.txt
robustintelligence-2.13.2.dist-info/RECORD
