Metadata-Version: 2.1
Name: robustintelligence
Version: 2.13.2
Summary: Robust Intelligence REST API SDK
Maintainer-email: Robust Intelligence <support@robustintelligence.com>
Keywords: Robust Intelligence REST API SDK,Robust Intelligence SDK
Classifier: License :: OSI Approved :: Apache Software License
Requires-Python: >=3.7
Requires-Dist: deprecated<2.0.0,>=1.0.0
Requires-Dist: python-dateutil==2.9.0.post0
Requires-Dist: pydantic<3,>=2
Requires-Dist: urllib3<2.1.0,>=1.25.3
